{
    "sensor2": {"01324180": [
        {"averageAccX": -6.010917642794761},
        {"averageAccY": 6.81003288646288},
        {"averageAccZ": 2.1925536616855923},
        {"stdAccX": 0.2728745321223178},
        {"stdAccY": 0.12856427384253735},
        {"stdAccZ": 0.017768101160588946},
        {"medianAccX": -5.78921},
        {"medianAccY": 7.52309},
        {"medianAccZ": 2.44963},
        {"rangeAccX": 29.13968},
        {"rangeAccY": 48.6642},
        {"rangeAccZ": 18.97803},
        {"maxAccX": 8.72188},
        {"maxAccY": 24.9754},
        {"maxAccZ": 14.7524},
        {"minAccX": -20.4178},
        {"minAccY": -23.6888},
        {"minAccZ": -4.22563}
    ]},
    "sensor0": {"01324189": [
        {"averageAccX": -9.184266826200886},
        {"averageAccY": -0.1254901885938865},
        {"averageAccZ": -1.759602658287339},
        {"stdAccX": 0.008807315595892774},
        {"stdAccY": 0.012176817321097396},
        {"stdAccZ": 0.03338371921241027},
        {"medianAccX": -9.3662},
        {"medianAccY": -1.28684},
        {"medianAccZ": -1.9128},
        {"rangeAccX": 24.65538},
        {"rangeAccY": 59.3119},
        {"rangeAccZ": 23.01981},
        {"maxAccX": 3.72848},
        {"maxAccY": 24.5131},
        {"maxAccZ": 9.04841},
        {"minAccX": -20.9269},
        {"minAccY": -34.7988},
        {"minAccZ": -13.9714}
    ]},
    "sensor1": {"01324188": [
        {"averageAccX": -4.716887041048038},
        {"averageAccY": 6.4754688245764305},
        {"averageAccZ": 0.48689762605240083},
        {"stdAccX": 0.1354916704749269},
        {"stdAccY": 0.21309783517649752},
        {"stdAccZ": 0.05408444612377306},
        {"medianAccX": -2.74268},
        {"medianAccY": 9.26236},
        {"medianAccZ": 0.853158},
        {"rangeAccX": 13.2408},
        {"rangeAccY": 27.5272},
        {"rangeAccZ": 7.68548},
        {"maxAccX": 4.9E-324},
        {"maxAccY": 16.2334},
        {"maxAccZ": 3.55267},
        {"minAccX": -13.2408},
        {"minAccY": -11.2938},
        {"minAccZ": -4.13281}
    ]}
}